drowse/__init__.py
drowse/drowse.py
drowse-0.2.0.dist-info/METADATA
drowse-0.2.0.dist-info/RECORD
drowse-0.2.0.dist-info/WHEEL
drowse-0.2.0.dist-info/top_level.txt
