Metadata-Version: 2.1
Name: drowse
Version: 0.2.0
Summary: Human readable slim REST client
Home-page: https://github.com/lgaggini/drowse
Author: Lorenzo Gaggini
Author-email: lg@lgaggini.net
License: LICENSE
Keywords: REST,API,HTTP
Platform: UNKNOWN
Classifier: Programming Language :: Python
Classifier: Development Status :: 4 - Beta
Classifier: Environment :: Other Environment
Classifier: Intended Audience :: Developers
Classifier: License :: OSI Approved :: GNU General Public License v3 (GPLv3)
Classifier: Operating System :: OS Independent
Classifier: Topic :: Internet :: WWW/HTTP
Requires-Dist: requests
